scanner.py
escl_scanner_cli-0.2.1.dist-info/LICENSE
escl_scanner_cli-0.2.1.dist-info/METADATA
escl_scanner_cli-0.2.1.dist-info/WHEEL
escl_scanner_cli-0.2.1.dist-info/entry_points.txt
escl_scanner_cli-0.2.1.dist-info/top_level.txt
escl_scanner_cli-0.2.1.dist-info/RECORD
