Metadata-Version: 2.2
Name: escl-scanner-cli
Version: 0.2.1
Summary: Control eSCL network scanners using a CLI utility
Home-page: https://github.com/PJK/escl-scanner-cli
Author: https://github.com/zegman, Pavel Kalvoda
Author-email: me@pavelkalvoda.com
License: Apache
License-File: LICENSE
Requires-Dist: requests
Requires-Dist: xmltodict
Requires-Dist: zeroconf
Dynamic: author
Dynamic: author-email
Dynamic: description
Dynamic: description-content-type
Dynamic: home-page
Dynamic: license
Dynamic: requires-dist
Dynamic: summary
